{
"students": 
	[
		{
			"id": 100,
			"fName": "Jackie",
			"lName": "Doe",
			"score": 453
		},
		{
			"id": 125,
			"fName": "Jackie",
			"lName": "Doe",
			"score": 453
		},
		{
			"id": 127,
			"fName": "Jony",
			"lName": "Doe",
			"score": 450

		},
		{
			"id": 2,
			"fName": "Jony",
			"lName": "Doe",
			"score": 450

		},

		{

			"id": 121,
			"fName": "Ram",
			"lName": "Moew",
			"score": 453
		},
		{

			"id": 122,
			"fName": "Mickey ",
			"lName": "Mouse",
			"score": 453
		},
		{

			"id": 130,
			"fName": "Donald",
			"lName": "Duck",
			"score": 453
		},
		{

			"id": 132,
			"fName": "Renuka ",
			"lName": "Mouse",
			"score": 453
		},
		{

			"id": 14,
			"fName": "Donald",
			"lName": "Duck",
			"score": 453
		},
		{
			"id": 1001,
			"fName": "Jackie",
			"lName": "Doe",
			"score": 453
		},
		{
			"id": 1251,
			"fName": "Jackie",
			"lName": "Doe",
			"score": 453
		},
		{
			"id": 1271,
			"fName": "Jony",
			"lName": "Doe",
			"score": 450

		},
		{
			"id": 21223,
			"fName": "Jony",
			"lName": "Doe",
			"score": 450

		},

		{

			"id": 12145,
			"fName": "Ram",
			"lName": "Moew",
			"score": 453
		},
		{

			"id": 12255,
			"fName": "Mickey ",
			"lName": "Mouse",
			"score": 453
		},
		{

			"id": 13023,
			"fName": "Donald",
			"lName": "Duck",
			"score": 453
		},
		{

			"id": 13289,
			"fName": "Renuka ",
			"lName": "Mouse",
			"score": 453
		},
		{

			"id": 1423,
			"fName": "Donald",
			"lName": "Duck",
			"score": 453
		},
		{
			"id": 10034,
			"fName": "Jackie",
			"lName": "Doe",
			"score": 453
		},
		{
			"id": 12545,
			"fName": "Jackie",
			"lName": "Doe",
			"score": 453
		},
		{
			"id": 12767,
			"fName": "Jony",
			"lName": "Doe",
			"score": 450

		},
		{
			"id": 2234,
			"fName": "Jony",
			"lName": "Doe",
			"score": 450

		},

		{

			"id": 12451,
			"fName": "Ram",
			"lName": "Moew",
			"score": 453
		},
		{

			"id": 12782,
			"fName": "Mickey ",
			"lName": "Mouse",
			"score": 453
		},
		{

			"id": 13065,
			"fName": "Donald",
			"lName": "Duck",
			"score": 453
		},
		{

			"id": 13342,
			"fName": "Renuka ",
			"lName": "Mouse",
			"score": 453
		},
		{
			"id": 1234,
			"fName": "Donald",
			"lName": "Duck",
			"score": 453
		}
		
	]
}